[
  {
    "ticker": "BND",
    "timestamp": "2026-04-01T09:53:07.589Z",
    "recordDate": "2026-04-01",
    "exDividendDate": "2026-04-01",
    "payableDate": "2026-04-06",
    "totalDistribution": 0.250016,
    "ordinaryIncome": 0.250016
  },
  {
    "ticker": "BND",
    "timestamp": "2026-04-01T09:53:07.589Z",
    "recordDate": "2026-03-02",
    "exDividendDate": "2026-03-02",
    "payableDate": "2026-03-04",
    "totalDistribution": 0.227824,
    "ordinaryIncome": 0.227824
  },
  {
    "ticker": "BND",
    "timestamp": "2026-04-01T09:53:07.589Z",
    "recordDate": "2026-02-02",
    "exDividendDate": "2026-02-02",
    "payableDate": "2026-02-04",
    "totalDistribution": 0.24547,
    "ordinaryIncome": 0.24547
  },
  {
    "ticker": "BND",
    "timestamp": "2026-04-01T09:53:07.589Z",
    "recordDate": "2025-12-18",
    "exDividendDate": "2025-12-18",
    "payableDate": "2025-12-22",
    "totalDistribution": 0.246638,
    "ordinaryIncome": 0.246638
  },
  {
    "ticker": "BND",
    "timestamp": "2026-04-01T09:53:07.589Z",
    "recordDate": "2025-12-01",
    "exDividendDate": "2025-12-01",
    "payableDate": "2025-12-03",
    "totalDistribution": 0.238572,
    "ordinaryIncome": 0.238572
  },
  {
    "ticker": "BND",
    "timestamp": "2026-04-01T09:53:07.589Z",
    "recordDate": "2025-11-03",
    "exDividendDate": "2025-11-03",
    "payableDate": "2025-11-05",
    "totalDistribution": 0.243631,
    "ordinaryIncome": 0.243631
  },
  {
    "ticker": "BND",
    "timestamp": "2026-04-01T09:53:07.589Z",
    "recordDate": "2025-10-01",
    "exDividendDate": "2025-10-01",
    "payableDate": "2025-10-03",
    "totalDistribution": 0.237328,
    "ordinaryIncome": 0.237328
  },
  {
    "ticker": "BND",
    "timestamp": "2026-04-01T09:53:07.589Z",
    "recordDate": "2025-09-02",
    "exDividendDate": "2025-09-02",
    "payableDate": "2025-09-04",
    "totalDistribution": 0.242759,
    "ordinaryIncome": 0.242759
  },
  {
    "ticker": "BND",
    "timestamp": "2026-04-01T09:53:07.589Z",
    "recordDate": "2025-08-01",
    "exDividendDate": "2025-08-01",
    "payableDate": "2025-08-05",
    "totalDistribution": 0.241866,
    "ordinaryIncome": 0.241866
  },
  {
    "ticker": "BND",
    "timestamp": "2026-04-01T09:53:07.589Z",
    "recordDate": "2025-07-01",
    "exDividendDate": "2025-07-01",
    "payableDate": "2025-07-03",
    "totalDistribution": 0.235347,
    "ordinaryIncome": 0.235347
  },
  {
    "ticker": "BND",
    "timestamp": "2026-04-01T09:53:07.589Z",
    "recordDate": "2025-06-02",
    "exDividendDate": "2025-06-02",
    "payableDate": "2025-06-04",
    "totalDistribution": 0.240315,
    "ordinaryIncome": 0.240315
  },
  {
    "ticker": "BND",
    "timestamp": "2026-04-01T09:53:07.589Z",
    "recordDate": "2025-05-01",
    "exDividendDate": "2025-05-01",
    "payableDate": "2025-05-05",
    "totalDistribution": 0.236371,
    "ordinaryIncome": 0.236371
  },
  {
    "ticker": "BND",
    "timestamp": "2026-04-01T09:53:07.589Z",
    "recordDate": "2025-04-01",
    "exDividendDate": "2025-04-01",
    "payableDate": "2025-04-03",
    "totalDistribution": 0.240374,
    "ordinaryIncome": 0.240374
  },
  {
    "ticker": "BND",
    "timestamp": "2026-04-01T09:53:07.589Z",
    "recordDate": "2025-03-03",
    "exDividendDate": "2025-03-03",
    "payableDate": "2025-03-05",
    "totalDistribution": 0.21946,
    "ordinaryIncome": 0.21946
  },
  {
    "ticker": "BND",
    "timestamp": "2026-04-01T09:53:07.589Z",
    "recordDate": "2025-02-03",
    "exDividendDate": "2025-02-03",
    "payableDate": "2025-02-05",
    "totalDistribution": 0.234799,
    "ordinaryIncome": 0.234799
  },
  {
    "ticker": "BND",
    "timestamp": "2026-04-01T09:53:07.589Z",
    "recordDate": "2024-12-24",
    "exDividendDate": "2024-12-24",
    "payableDate": "2024-12-27",
    "totalDistribution": 0.233378,
    "ordinaryIncome": 0.233378
  },
  {
    "ticker": "BND",
    "timestamp": "2026-04-01T09:53:07.589Z",
    "recordDate": "2024-12-02",
    "exDividendDate": "2024-12-02",
    "payableDate": "2024-12-04",
    "totalDistribution": 0.222928,
    "ordinaryIncome": 0.222928
  },
  {
    "ticker": "BND",
    "timestamp": "2026-04-01T09:53:07.589Z",
    "recordDate": "2024-11-01",
    "exDividendDate": "2024-11-01",
    "payableDate": "2024-11-05",
    "totalDistribution": 0.227631,
    "ordinaryIncome": 0.227631
  },
  {
    "ticker": "BND",
    "timestamp": "2026-04-01T09:53:07.589Z",
    "recordDate": "2024-10-01",
    "exDividendDate": "2024-10-01",
    "payableDate": "2024-10-03",
    "totalDistribution": 0.220705,
    "ordinaryIncome": 0.220705
  },
  {
    "ticker": "BND",
    "timestamp": "2026-04-01T09:53:07.589Z",
    "recordDate": "2024-09-03",
    "exDividendDate": "2024-09-03",
    "payableDate": "2024-09-05",
    "totalDistribution": 0.225518,
    "ordinaryIncome": 0.225518
  },
  {
    "ticker": "BND",
    "timestamp": "2026-04-01T09:53:07.589Z",
    "recordDate": "2024-08-01",
    "exDividendDate": "2024-08-01",
    "payableDate": "2024-08-05",
    "totalDistribution": 0.223909,
    "ordinaryIncome": 0.223909
  },
  {
    "ticker": "BND",
    "timestamp": "2026-04-01T09:53:07.589Z",
    "recordDate": "2024-07-01",
    "exDividendDate": "2024-07-01",
    "payableDate": "2024-07-03",
    "totalDistribution": 0.220702,
    "ordinaryIncome": 0.220702
  },
  {
    "ticker": "BND",
    "timestamp": "2026-04-01T09:53:07.589Z",
    "recordDate": "2024-06-03",
    "exDividendDate": "2024-06-03",
    "payableDate": "2024-06-05",
    "totalDistribution": 0.218966,
    "ordinaryIncome": 0.218966
  },
  {
    "ticker": "BND",
    "timestamp": "2026-04-01T09:53:07.589Z",
    "recordDate": "2024-05-02",
    "exDividendDate": "2024-05-01",
    "payableDate": "2024-05-06",
    "totalDistribution": 0.213811,
    "ordinaryIncome": 0.213811
  },
  {
    "ticker": "BND",
    "timestamp": "2026-04-01T09:53:07.589Z",
    "recordDate": "2024-04-02",
    "exDividendDate": "2024-04-01",
    "payableDate": "2024-04-04",
    "totalDistribution": 0.2163,
    "ordinaryIncome": 0.2163
  },
  {
    "ticker": "BND",
    "timestamp": "2026-04-01T09:53:07.589Z",
    "recordDate": "2024-03-04",
    "exDividendDate": "2024-03-01",
    "payableDate": "2024-03-06",
    "totalDistribution": 0.202321,
    "ordinaryIncome": 0.202321
  },
  {
    "ticker": "BND",
    "timestamp": "2026-04-01T09:53:07.589Z",
    "recordDate": "2024-02-02",
    "exDividendDate": "2024-02-01",
    "payableDate": "2024-02-06",
    "totalDistribution": 0.21188,
    "ordinaryIncome": 0.21188
  },
  {
    "ticker": "BND",
    "timestamp": "2026-04-01T09:53:07.589Z",
    "recordDate": "2023-12-26",
    "exDividendDate": "2023-12-22",
    "payableDate": "2023-12-28",
    "totalDistribution": 0.210541,
    "ordinaryIncome": 0.210541
  },
  {
    "ticker": "BND",
    "timestamp": "2026-04-01T09:53:07.589Z",
    "recordDate": "2023-12-04",
    "exDividendDate": "2023-12-01",
    "payableDate": "2023-12-06",
    "totalDistribution": 0.200957,
    "ordinaryIncome": 0.200957
  },
  {
    "ticker": "BND",
    "timestamp": "2026-04-01T09:53:07.589Z",
    "recordDate": "2023-11-02",
    "exDividendDate": "2023-11-01",
    "payableDate": "2023-11-06",
    "totalDistribution": 0.202776,
    "ordinaryIncome": 0.202776
  },
  {
    "ticker": "BND",
    "timestamp": "2026-04-01T09:53:07.589Z",
    "recordDate": "2023-10-03",
    "exDividendDate": "2023-10-02",
    "payableDate": "2023-10-05",
    "totalDistribution": 0.192499,
    "ordinaryIncome": 0.192499
  },
  {
    "ticker": "BND",
    "timestamp": "2026-04-01T09:53:07.589Z",
    "recordDate": "2023-09-05",
    "exDividendDate": "2023-09-01",
    "payableDate": "2023-09-07",
    "totalDistribution": 0.195733,
    "ordinaryIncome": 0.195733
  },
  {
    "ticker": "BND",
    "timestamp": "2026-04-01T09:53:07.589Z",
    "recordDate": "2023-08-02",
    "exDividendDate": "2023-08-01",
    "payableDate": "2023-08-04",
    "totalDistribution": 0.19266,
    "ordinaryIncome": 0.19266
  },
  {
    "ticker": "BND",
    "timestamp": "2026-04-01T09:53:07.589Z",
    "recordDate": "2023-07-05",
    "exDividendDate": "2023-07-03",
    "payableDate": "2023-07-07",
    "totalDistribution": 0.184372,
    "ordinaryIncome": 0.184372
  },
  {
    "ticker": "BND",
    "timestamp": "2026-04-01T09:53:07.589Z",
    "recordDate": "2023-06-02",
    "exDividendDate": "2023-06-01",
    "payableDate": "2023-06-06",
    "totalDistribution": 0.186964,
    "ordinaryIncome": 0.186964
  },
  {
    "ticker": "BND",
    "timestamp": "2026-04-01T09:53:07.589Z",
    "recordDate": "2023-05-02",
    "exDividendDate": "2023-05-01",
    "payableDate": "2023-05-04",
    "totalDistribution": 0.179745,
    "ordinaryIncome": 0.179745
  },
  {
    "ticker": "BND",
    "timestamp": "2026-04-01T09:53:07.589Z",
    "recordDate": "2023-04-04",
    "exDividendDate": "2023-04-03",
    "payableDate": "2023-04-06",
    "totalDistribution": 0.182803,
    "ordinaryIncome": 0.182803
  },
  {
    "ticker": "BND",
    "timestamp": "2026-04-01T09:53:07.589Z",
    "recordDate": "2023-03-02",
    "exDividendDate": "2023-03-01",
    "payableDate": "2023-03-06",
    "totalDistribution": 0.164216,
    "ordinaryIncome": 0.164216
  },
  {
    "ticker": "BND",
    "timestamp": "2026-04-01T09:53:07.589Z",
    "recordDate": "2023-02-02",
    "exDividendDate": "2023-02-01",
    "payableDate": "2023-02-06",
    "totalDistribution": 0.175962,
    "ordinaryIncome": 0.175962
  },
  {
    "ticker": "BND",
    "timestamp": "2026-04-01T09:53:07.589Z",
    "recordDate": "2022-12-27",
    "exDividendDate": "2022-12-23",
    "payableDate": "2022-12-29",
    "totalDistribution": 0.172311,
    "ordinaryIncome": 0.172311
  },
  {
    "ticker": "BND",
    "timestamp": "2026-04-01T09:53:07.589Z",
    "recordDate": "2022-12-02",
    "exDividendDate": "2022-12-01",
    "payableDate": "2022-12-06",
    "totalDistribution": 0.164606,
    "ordinaryIncome": 0.164606
  },
  {
    "ticker": "BND",
    "timestamp": "2026-04-01T09:53:07.589Z",
    "recordDate": "2022-11-02",
    "exDividendDate": "2022-11-01",
    "payableDate": "2022-11-04",
    "totalDistribution": 0.162861,
    "ordinaryIncome": 0.162861
  },
  {
    "ticker": "BND",
    "timestamp": "2026-04-01T09:53:07.589Z",
    "recordDate": "2022-10-04",
    "exDividendDate": "2022-10-03",
    "payableDate": "2022-10-06",
    "totalDistribution": 0.156129,
    "ordinaryIncome": 0.156129
  },
  {
    "ticker": "BND",
    "timestamp": "2026-04-01T09:53:07.589Z",
    "recordDate": "2022-09-02",
    "exDividendDate": "2022-09-01",
    "payableDate": "2022-09-07",
    "totalDistribution": 0.15649,
    "ordinaryIncome": 0.15649
  },
  {
    "ticker": "BND",
    "timestamp": "2026-04-01T09:53:07.589Z",
    "recordDate": "2022-08-02",
    "exDividendDate": "2022-08-01",
    "payableDate": "2022-08-04",
    "totalDistribution": 0.153304,
    "ordinaryIncome": 0.153304
  },
  {
    "ticker": "BND",
    "timestamp": "2026-04-01T09:53:07.589Z",
    "recordDate": "2022-07-05",
    "exDividendDate": "2022-07-01",
    "payableDate": "2022-07-07",
    "totalDistribution": 0.148731,
    "ordinaryIncome": 0.148731
  },
  {
    "ticker": "BND",
    "timestamp": "2026-04-01T09:53:07.589Z",
    "recordDate": "2022-06-02",
    "exDividendDate": "2022-06-01",
    "payableDate": "2022-06-06",
    "totalDistribution": 0.148043,
    "ordinaryIncome": 0.148043
  },
  {
    "ticker": "BND",
    "timestamp": "2026-04-01T09:53:07.589Z",
    "recordDate": "2022-05-03",
    "exDividendDate": "2022-05-02",
    "payableDate": "2022-05-05",
    "totalDistribution": 0.140826,
    "ordinaryIncome": 0.140826
  },
  {
    "ticker": "BND",
    "timestamp": "2026-04-01T09:53:07.589Z",
    "recordDate": "2022-04-04",
    "exDividendDate": "2022-04-01",
    "payableDate": "2022-04-06",
    "totalDistribution": 0.198038,
    "ordinaryIncome": 0.138738,
    "ltcg": 0.0593
  },
  {
    "ticker": "BND",
    "timestamp": "2026-04-01T09:53:07.589Z",
    "recordDate": "2022-03-02",
    "exDividendDate": "2022-03-01",
    "payableDate": "2022-03-04",
    "totalDistribution": 0.129102,
    "ordinaryIncome": 0.129102
  },
  {
    "ticker": "BND",
    "timestamp": "2026-04-01T09:53:07.589Z",
    "recordDate": "2022-02-02",
    "exDividendDate": "2022-02-01",
    "payableDate": "2022-02-04",
    "totalDistribution": 0.136538,
    "ordinaryIncome": 0.136538
  },
  {
    "ticker": "BND",
    "timestamp": "2026-04-01T09:53:07.589Z",
    "recordDate": "2021-12-27",
    "exDividendDate": "2021-12-23",
    "payableDate": "2021-12-29",
    "totalDistribution": 0.270851,
    "ordinaryIncome": 0.140851,
    "ltcg": 0.13
  },
  {
    "ticker": "BND",
    "timestamp": "2026-04-01T09:53:07.589Z",
    "recordDate": "2021-12-02",
    "exDividendDate": "2021-12-01",
    "payableDate": "2021-12-06",
    "totalDistribution": 0.134923,
    "ordinaryIncome": 0.134923
  },
  {
    "ticker": "BND",
    "timestamp": "2026-04-01T09:53:07.589Z",
    "recordDate": "2021-11-02",
    "exDividendDate": "2021-11-01",
    "payableDate": "2021-11-04",
    "totalDistribution": 0.134025,
    "ordinaryIncome": 0.134025
  },
  {
    "ticker": "BND",
    "timestamp": "2026-04-01T09:53:07.589Z",
    "recordDate": "2021-10-04",
    "exDividendDate": "2021-10-01",
    "payableDate": "2021-10-06",
    "totalDistribution": 0.130203,
    "ordinaryIncome": 0.130203
  },
  {
    "ticker": "BND",
    "timestamp": "2026-04-01T09:53:07.589Z",
    "recordDate": "2021-09-02",
    "exDividendDate": "2021-09-01",
    "payableDate": "2021-09-07",
    "totalDistribution": 0.135029,
    "ordinaryIncome": 0.135029
  },
  {
    "ticker": "BND",
    "timestamp": "2026-04-01T09:53:07.589Z",
    "recordDate": "2021-08-03",
    "exDividendDate": "2021-08-02",
    "payableDate": "2021-08-05",
    "totalDistribution": 0.136095,
    "ordinaryIncome": 0.136095
  },
  {
    "ticker": "BND",
    "timestamp": "2026-04-01T09:53:07.589Z",
    "recordDate": "2021-07-02",
    "exDividendDate": "2021-07-01",
    "payableDate": "2021-07-07",
    "totalDistribution": 0.132101,
    "ordinaryIncome": 0.132101
  },
  {
    "ticker": "BND",
    "timestamp": "2026-04-01T09:53:07.589Z",
    "recordDate": "2021-06-02",
    "exDividendDate": "2021-06-01",
    "payableDate": "2021-06-04",
    "totalDistribution": 0.134483,
    "ordinaryIncome": 0.134483
  },
  {
    "ticker": "BND",
    "timestamp": "2026-04-01T09:53:07.589Z",
    "recordDate": "2021-05-04",
    "exDividendDate": "2021-05-03",
    "payableDate": "2021-05-06",
    "totalDistribution": 0.13057,
    "ordinaryIncome": 0.13057
  },
  {
    "ticker": "BND",
    "timestamp": "2026-04-01T09:53:07.589Z",
    "recordDate": "2021-04-05",
    "exDividendDate": "2021-04-01",
    "payableDate": "2021-04-07",
    "totalDistribution": 0.192453,
    "ordinaryIncome": 0.139053,
    "stcg": 0.0034,
    "ltcg": 0.05
  },
  {
    "ticker": "BND",
    "timestamp": "2026-04-01T09:53:07.589Z",
    "recordDate": "2021-03-02",
    "exDividendDate": "2021-03-01",
    "payableDate": "2021-03-04",
    "totalDistribution": 0.12875,
    "ordinaryIncome": 0.12875
  },
  {
    "ticker": "BND",
    "timestamp": "2026-04-01T09:53:07.589Z",
    "recordDate": "2021-02-02",
    "exDividendDate": "2021-02-01",
    "payableDate": "2021-02-04",
    "totalDistribution": 0.139196,
    "ordinaryIncome": 0.139196
  },
  {
    "ticker": "BND",
    "timestamp": "2026-04-01T09:53:07.589Z",
    "recordDate": "2020-12-24",
    "exDividendDate": "2020-12-23",
    "payableDate": "2020-12-29",
    "totalDistribution": 0.290782,
    "ordinaryIncome": 0.147182,
    "stcg": 0.0372,
    "ltcg": 0.1064
  },
  {
    "ticker": "BND",
    "timestamp": "2026-04-01T09:53:07.589Z",
    "recordDate": "2020-12-02",
    "exDividendDate": "2020-12-01",
    "payableDate": "2020-12-04",
    "totalDistribution": 0.143226,
    "ordinaryIncome": 0.143226
  },
  {
    "ticker": "BND",
    "timestamp": "2026-04-01T09:53:07.589Z",
    "recordDate": "2020-11-03",
    "exDividendDate": "2020-11-02",
    "payableDate": "2020-11-05",
    "totalDistribution": 0.150971,
    "ordinaryIncome": 0.150971
  },
  {
    "ticker": "BND",
    "timestamp": "2026-04-01T09:53:07.589Z",
    "recordDate": "2020-10-02",
    "exDividendDate": "2020-10-01",
    "payableDate": "2020-10-06",
    "totalDistribution": 0.150293,
    "ordinaryIncome": 0.150293
  },
  {
    "ticker": "BND",
    "timestamp": "2026-04-01T09:53:07.589Z",
    "recordDate": "2020-09-02",
    "exDividendDate": "2020-09-01",
    "payableDate": "2020-09-04",
    "totalDistribution": 0.153067,
    "ordinaryIncome": 0.153067
  },
  {
    "ticker": "BND",
    "timestamp": "2026-04-01T09:53:07.589Z",
    "recordDate": "2020-08-04",
    "exDividendDate": "2020-08-03",
    "payableDate": "2020-08-06",
    "totalDistribution": 0.15874,
    "ordinaryIncome": 0.15874
  },
  {
    "ticker": "BND",
    "timestamp": "2026-04-01T09:53:07.589Z",
    "recordDate": "2020-07-02",
    "exDividendDate": "2020-07-01",
    "payableDate": "2020-07-07",
    "totalDistribution": 0.162394,
    "ordinaryIncome": 0.162394
  },
  {
    "ticker": "BND",
    "timestamp": "2026-04-01T09:53:07.589Z",
    "recordDate": "2020-06-02",
    "exDividendDate": "2020-06-01",
    "payableDate": "2020-06-04",
    "totalDistribution": 0.168739,
    "ordinaryIncome": 0.168739
  },
  {
    "ticker": "BND",
    "timestamp": "2026-04-01T09:53:07.589Z",
    "recordDate": "2020-05-04",
    "exDividendDate": "2020-05-01",
    "payableDate": "2020-05-06",
    "totalDistribution": 0.173849,
    "ordinaryIncome": 0.173849
  },
  {
    "ticker": "BND",
    "timestamp": "2026-04-01T09:53:07.589Z",
    "recordDate": "2020-04-02",
    "exDividendDate": "2020-04-01",
    "payableDate": "2020-04-06",
    "totalDistribution": 0.190462,
    "ordinaryIncome": 0.190462
  },
  {
    "ticker": "BND",
    "timestamp": "2026-04-01T09:53:07.589Z",
    "recordDate": "2020-03-03",
    "exDividendDate": "2020-03-02",
    "payableDate": "2020-03-05",
    "totalDistribution": 0.172749,
    "ordinaryIncome": 0.172749
  },
  {
    "ticker": "BND",
    "timestamp": "2026-04-01T09:53:07.589Z",
    "recordDate": "2020-02-04",
    "exDividendDate": "2020-02-03",
    "payableDate": "2020-02-06",
    "totalDistribution": 0.182502,
    "ordinaryIncome": 0.182502
  },
  {
    "ticker": "BND",
    "timestamp": "2026-04-01T09:53:07.589Z",
    "recordDate": "2019-12-24",
    "exDividendDate": "2019-12-23",
    "payableDate": "2019-12-27",
    "totalDistribution": 0.187284,
    "ordinaryIncome": 0.187284
  },
  {
    "ticker": "BND",
    "timestamp": "2026-04-01T09:53:07.589Z",
    "recordDate": "2019-12-03",
    "exDividendDate": "2019-12-02",
    "payableDate": "2019-12-05",
    "totalDistribution": 0.179979,
    "ordinaryIncome": 0.179979
  },
  {
    "ticker": "BND",
    "timestamp": "2026-04-01T09:53:07.589Z",
    "recordDate": "2019-11-04",
    "exDividendDate": "2019-11-01",
    "payableDate": "2019-11-06",
    "totalDistribution": 0.185305,
    "ordinaryIncome": 0.185305
  },
  {
    "ticker": "BND",
    "timestamp": "2026-04-01T09:53:07.589Z",
    "recordDate": "2019-10-02",
    "exDividendDate": "2019-10-01",
    "payableDate": "2019-10-04",
    "totalDistribution": 0.181656,
    "ordinaryIncome": 0.181656
  },
  {
    "ticker": "BND",
    "timestamp": "2026-04-01T09:53:07.589Z",
    "recordDate": "2019-09-04",
    "exDividendDate": "2019-09-03",
    "payableDate": "2019-09-06",
    "totalDistribution": 0.188198,
    "ordinaryIncome": 0.188198
  },
  {
    "ticker": "BND",
    "timestamp": "2026-04-01T09:53:07.589Z",
    "recordDate": "2019-08-02",
    "exDividendDate": "2019-08-01",
    "payableDate": "2019-08-06",
    "totalDistribution": 0.193413,
    "ordinaryIncome": 0.193413
  },
  {
    "ticker": "BND",
    "timestamp": "2026-04-01T09:53:07.589Z",
    "recordDate": "2019-07-02",
    "exDividendDate": "2019-07-01",
    "payableDate": "2019-07-05",
    "totalDistribution": 0.194464,
    "ordinaryIncome": 0.194464
  },
  {
    "ticker": "BND",
    "timestamp": "2026-04-01T09:53:07.589Z",
    "recordDate": "2019-06-04",
    "exDividendDate": "2019-06-03",
    "payableDate": "2019-06-06",
    "totalDistribution": 0.19348,
    "ordinaryIncome": 0.19348
  },
  {
    "ticker": "BND",
    "timestamp": "2026-04-01T09:53:07.589Z",
    "recordDate": "2019-05-02",
    "exDividendDate": "2019-05-01",
    "payableDate": "2019-05-06",
    "totalDistribution": 0.194785,
    "ordinaryIncome": 0.194785
  },
  {
    "ticker": "BND",
    "timestamp": "2026-04-01T09:53:07.589Z",
    "recordDate": "2019-04-02",
    "exDividendDate": "2019-04-01",
    "payableDate": "2019-04-04",
    "totalDistribution": 0.199608,
    "ordinaryIncome": 0.199608
  },
  {
    "ticker": "BND",
    "timestamp": "2026-04-01T09:53:07.589Z",
    "recordDate": "2019-03-04",
    "exDividendDate": "2019-03-01",
    "payableDate": "2019-03-06",
    "totalDistribution": 0.183666,
    "ordinaryIncome": 0.183666
  },
  {
    "ticker": "BND",
    "timestamp": "2026-04-01T09:53:07.589Z",
    "recordDate": "2019-02-04",
    "exDividendDate": "2019-02-01",
    "payableDate": "2019-02-06",
    "totalDistribution": 0.198345,
    "ordinaryIncome": 0.198345
  },
  {
    "ticker": "BND",
    "timestamp": "2026-04-01T09:53:07.589Z",
    "recordDate": "2018-12-26",
    "exDividendDate": "2018-12-24",
    "payableDate": "2018-12-28",
    "totalDistribution": 0.198316,
    "ordinaryIncome": 0.198316
  },
  {
    "ticker": "BND",
    "timestamp": "2026-04-01T09:53:07.589Z",
    "recordDate": "2018-12-04",
    "exDividendDate": "2018-12-03",
    "payableDate": "2018-12-06",
    "totalDistribution": 0.192026,
    "ordinaryIncome": 0.192026
  },
  {
    "ticker": "BND",
    "timestamp": "2026-04-01T09:53:07.589Z",
    "recordDate": "2018-11-02",
    "exDividendDate": "2018-11-01",
    "payableDate": "2018-11-06",
    "totalDistribution": 0.194369,
    "ordinaryIncome": 0.194369
  },
  {
    "ticker": "BND",
    "timestamp": "2026-04-01T09:53:07.589Z",
    "recordDate": "2018-10-02",
    "exDividendDate": "2018-10-01",
    "payableDate": "2018-10-04",
    "totalDistribution": 0.183416,
    "ordinaryIncome": 0.183416
  },
  {
    "ticker": "BND",
    "timestamp": "2026-04-01T09:53:07.589Z",
    "recordDate": "2018-09-05",
    "exDividendDate": "2018-09-04",
    "payableDate": "2018-09-07",
    "totalDistribution": 0.18764,
    "ordinaryIncome": 0.18764
  },
  {
    "ticker": "BND",
    "timestamp": "2026-04-01T09:53:07.589Z",
    "recordDate": "2018-08-02",
    "exDividendDate": "2018-08-01",
    "payableDate": "2018-08-06",
    "totalDistribution": 0.186858,
    "ordinaryIncome": 0.186858
  },
  {
    "ticker": "BND",
    "timestamp": "2026-04-01T09:53:07.589Z",
    "recordDate": "2018-07-03",
    "exDividendDate": "2018-07-02",
    "payableDate": "2018-07-06",
    "totalDistribution": 0.181007,
    "ordinaryIncome": 0.181007
  },
  {
    "ticker": "BND",
    "timestamp": "2026-04-01T09:53:07.589Z",
    "recordDate": "2018-06-04",
    "exDividendDate": "2018-06-01",
    "payableDate": "2018-06-06",
    "totalDistribution": 0.18462,
    "ordinaryIncome": 0.18462
  },
  {
    "ticker": "BND",
    "timestamp": "2026-04-01T09:53:07.589Z",
    "recordDate": "2018-05-02",
    "exDividendDate": "2018-05-01",
    "payableDate": "2018-05-04",
    "totalDistribution": 0.178358,
    "ordinaryIncome": 0.178358
  },
  {
    "ticker": "BND",
    "timestamp": "2026-04-01T09:53:07.589Z",
    "recordDate": "2018-04-03",
    "exDividendDate": "2018-04-02",
    "payableDate": "2018-04-05",
    "totalDistribution": 0.200173,
    "ordinaryIncome": 0.181013,
    "ltcg": 0.01916
  },
  {
    "ticker": "BND",
    "timestamp": "2026-04-01T09:53:07.589Z",
    "recordDate": "2018-03-02",
    "exDividendDate": "2018-03-01",
    "payableDate": "2018-03-06",
    "totalDistribution": 0.165345,
    "ordinaryIncome": 0.165345
  },
  {
    "ticker": "BND",
    "timestamp": "2026-04-01T09:53:07.589Z",
    "recordDate": "2018-02-02",
    "exDividendDate": "2018-02-01",
    "payableDate": "2018-02-06",
    "totalDistribution": 0.176624,
    "ordinaryIncome": 0.176624
  },
  {
    "ticker": "BND",
    "timestamp": "2026-04-01T09:53:07.589Z",
    "recordDate": "2017-12-27",
    "exDividendDate": "2017-12-26",
    "payableDate": "2017-12-29",
    "totalDistribution": 0.211219,
    "ordinaryIncome": 0.174219,
    "ltcg": 0.037
  },
  {
    "ticker": "BND",
    "timestamp": "2026-04-01T09:53:07.589Z",
    "recordDate": "2017-12-04",
    "exDividendDate": "2017-12-01",
    "payableDate": "2017-12-06",
    "totalDistribution": 0.168434,
    "ordinaryIncome": 0.168434
  },
  {
    "ticker": "BND",
    "timestamp": "2026-04-01T09:53:07.589Z",
    "recordDate": "2017-11-02",
    "exDividendDate": "2017-11-01",
    "payableDate": "2017-11-06",
    "totalDistribution": 0.172858,
    "ordinaryIncome": 0.172858
  },
  {
    "ticker": "BND",
    "timestamp": "2026-04-01T09:53:07.589Z",
    "recordDate": "2017-10-03",
    "exDividendDate": "2017-10-02",
    "payableDate": "2017-10-05",
    "totalDistribution": 0.16817,
    "ordinaryIncome": 0.16817
  },
  {
    "ticker": "BND",
    "timestamp": "2026-04-01T09:53:07.589Z",
    "recordDate": "2017-09-06",
    "exDividendDate": "2017-09-01",
    "payableDate": "2017-09-08",
    "totalDistribution": 0.173519,
    "ordinaryIncome": 0.173519
  },
  {
    "ticker": "BND",
    "timestamp": "2026-04-01T09:53:07.589Z",
    "recordDate": "2017-08-03",
    "exDividendDate": "2017-08-01",
    "payableDate": "2017-08-07",
    "totalDistribution": 0.17107,
    "ordinaryIncome": 0.17107
  },
  {
    "ticker": "BND",
    "timestamp": "2026-04-01T09:53:07.589Z",
    "recordDate": "2017-07-06",
    "exDividendDate": "2017-07-03",
    "payableDate": "2017-07-10",
    "totalDistribution": 0.169673,
    "ordinaryIncome": 0.169673
  },
  {
    "ticker": "BND",
    "timestamp": "2026-04-01T09:53:07.589Z",
    "recordDate": "2017-06-05",
    "exDividendDate": "2017-06-01",
    "payableDate": "2017-06-07",
    "totalDistribution": 0.172209,
    "ordinaryIncome": 0.172209
  },
  {
    "ticker": "BND",
    "timestamp": "2026-04-01T09:53:07.589Z",
    "recordDate": "2017-05-03",
    "exDividendDate": "2017-05-01",
    "payableDate": "2017-05-05",
    "totalDistribution": 0.167906,
    "ordinaryIncome": 0.167906
  },
  {
    "ticker": "BND",
    "timestamp": "2026-04-01T09:53:07.589Z",
    "recordDate": "2017-04-05",
    "exDividendDate": "2017-04-03",
    "payableDate": "2017-04-07",
    "totalDistribution": 0.173602,
    "ordinaryIncome": 0.173602
  },
  {
    "ticker": "BND",
    "timestamp": "2026-04-01T09:53:07.589Z",
    "recordDate": "2017-03-03",
    "exDividendDate": "2017-03-01",
    "payableDate": "2017-03-07",
    "totalDistribution": 0.158376,
    "ordinaryIncome": 0.158376
  },
  {
    "ticker": "BND",
    "timestamp": "2026-04-01T09:53:07.589Z",
    "recordDate": "2017-02-03",
    "exDividendDate": "2017-02-01",
    "payableDate": "2017-02-07",
    "totalDistribution": 0.168023,
    "ordinaryIncome": 0.168023
  },
  {
    "ticker": "BND",
    "timestamp": "2026-04-01T09:53:07.589Z",
    "recordDate": "2016-12-27",
    "exDividendDate": "2016-12-22",
    "payableDate": "2016-12-29",
    "totalDistribution": 0.205469,
    "ordinaryIncome": 0.169769,
    "stcg": 0.0243,
    "ltcg": 0.0114
  },
  {
    "ticker": "BND",
    "timestamp": "2026-04-01T09:53:07.589Z",
    "recordDate": "2016-12-05",
    "exDividendDate": "2016-12-01",
    "payableDate": "2016-12-07",
    "totalDistribution": 0.160291,
    "ordinaryIncome": 0.160291
  },
  {
    "ticker": "BND",
    "timestamp": "2026-04-01T09:53:07.589Z",
    "recordDate": "2016-11-03",
    "exDividendDate": "2016-11-01",
    "payableDate": "2016-11-07",
    "totalDistribution": 0.162502,
    "ordinaryIncome": 0.162502
  },
  {
    "ticker": "BND",
    "timestamp": "2026-04-01T09:53:07.589Z",
    "recordDate": "2016-10-05",
    "exDividendDate": "2016-10-03",
    "payableDate": "2016-10-07",
    "totalDistribution": 0.160539,
    "ordinaryIncome": 0.160539
  },
  {
    "ticker": "BND",
    "timestamp": "2026-04-01T09:53:07.589Z",
    "recordDate": "2016-09-06",
    "exDividendDate": "2016-09-01",
    "payableDate": "2016-09-08",
    "totalDistribution": 0.165906,
    "ordinaryIncome": 0.165906
  },
  {
    "ticker": "BND",
    "timestamp": "2026-04-01T09:53:07.589Z",
    "recordDate": "2016-08-03",
    "exDividendDate": "2016-08-01",
    "payableDate": "2016-08-05",
    "totalDistribution": 0.165464,
    "ordinaryIncome": 0.165464
  },
  {
    "ticker": "BND",
    "timestamp": "2026-04-01T09:53:07.589Z",
    "recordDate": "2016-07-06",
    "exDividendDate": "2016-07-01",
    "payableDate": "2016-07-08",
    "totalDistribution": 0.164362,
    "ordinaryIncome": 0.164362
  },
  {
    "ticker": "BND",
    "timestamp": "2026-04-01T09:53:07.589Z",
    "recordDate": "2016-06-03",
    "exDividendDate": "2016-06-01",
    "payableDate": "2016-06-07",
    "totalDistribution": 0.169178,
    "ordinaryIncome": 0.169178
  },
  {
    "ticker": "BND",
    "timestamp": "2026-04-01T09:53:07.589Z",
    "recordDate": "2016-05-04",
    "exDividendDate": "2016-05-02",
    "payableDate": "2016-05-06",
    "totalDistribution": 0.164101,
    "ordinaryIncome": 0.164101
  },
  {
    "ticker": "BND",
    "timestamp": "2026-04-01T09:53:07.589Z",
    "recordDate": "2016-04-05",
    "exDividendDate": "2016-04-01",
    "payableDate": "2016-04-07",
    "totalDistribution": 0.172864,
    "ordinaryIncome": 0.172864
  },
  {
    "ticker": "BND",
    "timestamp": "2026-03-02T05:38:17.342Z",
    "recordDate": "2016-03-03",
    "exDividendDate": "2016-03-01",
    "payableDate": "2016-03-07",
    "totalDistribution": 0.16545,
    "ordinaryIncome": 0.16545
  }
]
